balify/__init__.py
balify/auth.py
balify/cli.py
balify/decorators.py
balify/exceptions.py
balify/generic_routes.py
balify/paginate.py
balify/resource.py
balify/schemas.py
balify/utils.py
balify-0.0.2.dist-info/METADATA
balify-0.0.2.dist-info/WHEEL
balify-0.0.2.dist-info/entry_points.txt
balify-0.0.2.dist-info/licenses/LICENSE
balify-0.0.2.dist-info/RECORD
